juliapkg/__init__.py
juliapkg/__main__.py
juliapkg/cli.py
juliapkg/compat.py
juliapkg/deps.py
juliapkg/find_julia.py
juliapkg/install_julia.py
juliapkg/juliapkg.json
juliapkg/registry.py
juliapkg/state.py
juliapkg-0.1.22.dist-info/METADATA
juliapkg-0.1.22.dist-info/WHEEL
juliapkg-0.1.22.dist-info/licenses/LICENSE
juliapkg-0.1.22.dist-info/RECORD
