Metadata-Version: 2.4
Name: juliapkg
Version: 0.1.22
Summary: Julia version manager and package manager
Project-URL: Homepage, http://github.com/JuliaPy/pyjuliapkg
Project-URL: Repository, http://github.com/JuliaPy/pyjuliapkg.git
Project-URL: Issues, http://github.com/JuliaPy/pyjuliapkg/issues
Project-URL: Changelog, https://github.com/JuliaPy/pyjuliapkg/blob/main/CHANGELOG.md
Author: Christopher Doris
License-File: LICENSE
Classifier: License :: OSI Approved :: MIT License
Classifier: Programming Language :: Python :: 3
Requires-Python: >=3.9
Requires-Dist: filelock<4.0,>=3.16
Requires-Dist: semver<4.0,>=3.0
Requires-Dist: tomli<3.0,>=2.0
Requires-Dist: tomlkit<0.14,>=0.13.3
Provides-Extra: cli
Requires-Dist: click<9.0,>=8.0; extra == 'cli'
